entari_plugin_database-0.2.1.dist-info/METADATA
entari_plugin_database-0.2.1.dist-info/WHEEL
entari_plugin_database-0.2.1.dist-info/entry_points.txt
entari_plugin_database-0.2.1.dist-info/licenses/LICENSE
entari_plugin_database/README.md
entari_plugin_database/__init__.py
entari_plugin_database/config.py
entari_plugin_database/migration.py
entari_plugin_database/param.py
entari_plugin_database/utils.py
entari_plugin_database-0.2.1.dist-info/RECORD
