Metadata-Version: 2.1
Name: entari-plugin-database
Version: 0.2.1
Summary: Entari plugin for SQLAlchemy ORM
Author-Email: RF-Tar-Railt <rf_tar_railt@qq.com>
License: MIT
Requires-Python: >=3.10
Requires-Dist: sqlalchemy>=2.0.42
Requires-Dist: aiosqlite>=0.21.0
Requires-Dist: graia-amnesia>=0.11.4
Requires-Dist: tarina<0.8.0,>=0.7.1
Requires-Dist: arclet-entari<0.17.0,>=0.16.2
Requires-Dist: arclet-letoderea>=0.19.5
Requires-Dist: alembic>=1.16.5
